SmartThings/Account.py
SmartThings/__init__.py
tests/__init__.py
tests/test_Account.py
python_smartthings-1.0.0.dist-info/LICENSE
python_smartthings-1.0.0.dist-info/METADATA
python_smartthings-1.0.0.dist-info/WHEEL
python_smartthings-1.0.0.dist-info/top_level.txt
python_smartthings-1.0.0.dist-info/RECORD
