Metadata-Version: 2.1
Name: python-smartthings
Version: 1.0.0
Summary: A Python Package for Interacting with SmartThings
Home-page: https://github.com/kalebr3/python-smartthings
Author: Kaleb Redman
Author-email: dev@redman.us
License: UNKNOWN
Platform: UNKNOWN
Classifier: Programming Language :: Python :: 3
Classifier: License :: OSI Approved :: MIT License
Classifier: Operating System :: OS Independent
Requires-Python: >=3.7
Requires-Dist: requests
